{
  "lastUpdated": "2026-02-18T11:11:32Z",
  "totalResults": "911",
  "competitors": [
    {
      "rank": 1,
      "name": "Stray Kids (Dominate SKZOO) Keychains STL File",
      "shop": "KitsuneCraftiness",
      "price": "AU$4.07",
      "badge": null,
      "url": "https://www.etsy.com/au/listing/4345056272"
    },
    {
      "rank": 2,
      "name": "SKZOO 3D Printed Keycap | Stray Kids OT8 Collectible | KPOP Fan Gift | SKZ Merch Decor",
      "shop": "FATFACTORYCo",
      "price": "AU$9.46",
      "badge": null,
      "url": "https://www.etsy.com/au/listing/4435882256"
    },
    {
      "rank": 3,
      "name": "Skzoo 3D Figure, OT8, Skzoo Collectible, Stray Kids Gift, SKZ Merch, KPOP 3D Print",
      "shop": "Skzoowears",
      "price": "AU$22.02",
      "badge": null,
      "url": "https://www.etsy.com/au/listing/1760872939"
    },
    {
      "rank": 4,
      "name": "Stray Kids 3D print figures, Japan Toy World Fanmeeting, Stray Kids merch,3D collectible, skzoo 3D figure, SKZoo standee",
      "shop": "NRZbabySTAY",
      "price": "AU$11.83",
      "badge": null,
      "url": "https://www.etsy.com/au/listing/1754515963"
    },
    {
      "rank": 5,
      "name": "Wolf Chan 3D Printed Car Figurine | SKZOO 3D Printed Car Figurine | Stray Kids OT8 Collectible",
      "shop": "FATFACTORYCo",
      "price": "AU$17.02",
      "badge": "Limited stock",
      "url": "https://www.etsy.com/au/listing/1878770225"
    },
    {
      "rank": 6,
      "name": "3D File- KPOP Lightstick Stand for SKZ Stray Kids",
      "shop": "Eveandpysche",
      "price": "AU$8.13",
      "badge": null,
      "url": "https://www.etsy.com/au/listing/4327169916"
    },
    {
      "rank": 7,
      "name": "Han Quokka 3D Printed Car Figurine | SKZOO 3D Printed Car Figurine | Stray Kids OT8 Collectible",
      "shop": "FATFACTORYCo",
      "price": "AU$17.02",
      "badge": "Limited stock",
      "url": "https://www.etsy.com/au/listing/1867966532"
    },
    {
      "rank": 8,
      "name": "Stray Kids SKZoo mini 3D print figures",
      "shop": "NRZbabySTAY",
      "price": "AU$7.39",
      "badge": null,
      "url": "https://www.etsy.com/au/listing/1717667120"
    },
    {
      "rank": 9,
      "name": "Kpop Stray Kids Lightstick Phone MagSafe Grip| STAY Phone Stand| SKZ Gift",
      "shop": "KCASEROOM",
      "price": "AU$27.99",
      "badge": "Bestseller",
      "url": "https://www.etsy.com/au/listing/4416026628"
    },
    {
      "rank": 10,
      "name": "Skzoo Figures, Stray Kids Figure, 3D Printed SKZOO, Pilot Skzoo",
      "shop": "skzoowears",
      "price": "AU$13.16",
      "badge": null,
      "url": "https://www.etsy.com/au/listing/4357625983"
    }
  ]
}
